{
    "filename": "Свод правил 377.1325800.2017.pdf",
    "full_name": "Сооружения портовые. Правила эксплуатации",
    "number": "377.1325800.2017",
    "date_issue": "2018",
    "document_type": "Свод правил",
    "language": "Russian",
    "category": "Организация строительства",
    "source": "Свод правил 377.1325800.2017.pdf",
    "total_pages": 28,
    "status": "Действует",
    "pages": [
        {
            "page": 1,
            "page_content": "МИНИСТЕРСТВО СТРОИТЕЛЬСТВА \nИ ЖИЛИЩНО-КОММУНАЛЬНОГО ХОЗЯЙСТВА \nРОССИЙСКОЙ ФЕДЕРАЦИИ\nС В О Д  П Р А В И Л  \nСП 377.1325800.2017\nСООРУЖЕНИЯ ПОРТОВЫЕ \nПравила эксплуатации\nИздание официальное\nМосква\nСтандартинформ\n2018\nтн вэд"
        },
        {
            "page": 2,
            "page_content": "СП 377.1325800.2017\nПредисловие\nСведения о своде правил\n1 ИСПОЛНИТЕЛИ — АО «ВНИИГ им. Б.Е. Веденеева», АО «ЛЕНМОРНИИПРОЕКТ»\n2 ВНЕСЕН Техническим комитетом по стандартизации ТК 465 «Строительство»\n3 ПОДГОТОВЛЕН к утверждению Департаментом градостроительной деятельности и архитектуры \nМинистерства строительства и жилищно-коммунального хозяйства Российской Федерации (Минстрой \nРоссии)\n4 УТВЕРЖДЕН Приказом Министерства строительства и жилищно-коммунального хозяйства Рос­\nсийской Федерации от 11 декабря 2017 г. № 1641 /пр и введен в действие с 12 июня 2018 г.\n5 ЗАРЕГИСТРИРОВАН Федеральным агентством по техническому регулированию и метрологии \n(Росстандарт)\n6 ВВЕДЕН ВПЕРВЫЕ\nВ случае пересмотра (замены) или отмены настоящего свода правил соответствующее уве­\nдомление будет опубликовано в установленном порядке. Соответствующая информация, уведом­\nление и тексты размещаются также в информационной системе общего пользования — на офици­\nальном сайте разработчика (Минстрой России) в сети Интернет\n© Минстрой России, 2017 \n© Стандартинформ, оформление, 2018\nНастоящий свод правил не может быть полностью или частично воспроизведен, тиражирован и \nраспространен в качестве официального издания на территории Российской Федерации без разреше­\nния Минстроя России"
        },
        {
            "page": 3,
            "page_content": "СП 377.1325800.2017\nСодержание\n1 Область применения..........................................................................................................................................1\n2 Нормативные ссылки..........................................................................................................................................1\n3 Термины и определения................................................................................................................................... 2\n4 Общие положения..............................................................................................................................................3\n5 Охрана окружающей среды .............................................................................................................................5\n6 Портовые гидротехнические сооружения......................................................................................................6\n6.1 Режим эксплуатации................................................................................................................................... 6\n6.2 Техническое обслуживание.......................................................................................................................9\n6.3 Ремонт........................................................................................................................................................ 10\n7 Крытые склады ................................................................................................................................................10\n7.1 Режим эксплуатации................................................................................................................................. 10\n7.2 Техническое обслуживание..................................................................................................................... 11\n7.3 Ремонт........................................................................................................................................................ 12\n8 Открытые грузовые склады и дороги............................................................................................................ 12\n8.1 Режим эксплуатации................................................................................................................................. 12\n8.2 Техническое обслуживание.....................................................................................................................14\n8.3 Ремонт........................................................................................................................................................ 15\n9 Рельсовые крановые пути............................................................................................................................... 15\n9.1 Режим эксплуатации................................................................................................................................. 15\n9.2 Техническое обслуживание.....................................................................................................................16\n9.3 Ремонт........................................................................................................................................................ 17\n10 Прочие здания и сооружения.......................................................................................................................17\n10.1 Режим эксплуатации............................................................................................................................... 17\n10.2 Техническое обслуживание...................................................................................................................18\n10.3 Ремонт...................................................................................................................................................... 18\n11 Акватории и судоходные каналы.................................................................................................................19\n11.1 Режим эксплуатации............................................................................................................................... 19\n11.2 Техническое обслуживание...................................................................................................................20\n11.3 Ремонтные дноуглубительные работы................................................................................................20\nБиблиография......................................................................................................................................................22"
        },
        {
            "page": 4,
            "page_content": "СП 377.1325800.2017\nВведение\nНастоящий свод правил разработан в соответствии с требованиями федеральных законов от \n21 июля 1997 г. № 117-ФЗ «О безопасности гидротехнических сооружений», от 27 декабря 2002 г. \n№ 184-ФЗ «О техническом регулировании», от 30 декабря 2009 г. № 384-ФЗ «Технический регламент о \nбезопасности зданий и сооружений».\nСвод правил выполнен авторским коллективом АО «ВНИИГ им. Б.Е. Веденеева» (канд. техн. наук \nА.П. Пак — руководитель разработки, д-р техн. наук М.Е. Миронов), АО «ЛЕНМОРНИИПРОЕКТ»\n(М.В. Минин, В.В. Иванов).\nIV"
        },
        {
            "page": 5,
            "page_content": "СП 377.1325800.2017\nС В О Д  \nП\nР\nА\nВ\nИ\nЛ\nСООРУЖЕНИЯ ПОРТОВЫЕ \nПравила эксплуатации\nBuildings in the ports. The rules of exploitation\nДата введения — 2018—06—12\n1 Область применения\n1.1 Настоящий свод правил устанавливает общие требования и правила эксплуатации объектов \nинфраструктуры морского порта.\n1.2 Настоящий свод правил распространяется на портовые сооружения, крытые склады, откры­\nтые грузовые склады и дороги, рельсовые крановые пути, прочие производственные здания и сооруже­\nния, акватории и судоходные каналы морских портов и судоремонтных заводов.\n1.3 Свод правил не распространяется:\n- на буксиры, ледоколы и иные суда портового флота;\n- военные корабли;\n- стационарные или плавучие платформы либо морские подвижные буровые установки;\n- прогулочные суда;\n- оборудование, снабженное взрывчатыми веществами и пиротехникой;\n- средства навигационного оборудования и другие объекты навигационно-гидрографического \nобеспечения судоходных путей, системы управления движением судов, информационные системы, \nперегрузочное оборудование.\n2 Нормативные ссылки\nВ настоящем своде правил использованы нормативные ссылки на следующие документы:\nГОСТ 12.3.006—75 Система стандартов безопасности труда. Эксплуатация водопроводных и ка­\nнализационных сооружений и сетей. Общие требования безопасности\nГОСТ 12.4.026—2015 Система стандартов безопасности труда. Цвета сигнальные, знаки безопас­\nности и разметка сигнальная. Назначение и правила применения. Общие технические требования и \nхарактеристики. Методы испытаний\nГОСТ 2761—84 Источники централизованного хозяйственно-питьевого водоснабжения. Гигиени­\nческие, технические требования и правила выбора\nГОСТ 26600—98 Знаки навигационные внутренних судоходных путей. Общие технические условия \nГОСТ 27751—2014 Надежность строительных конструкций и оснований. Основные положения \nГОСТ Р 51232—98 Вода питьевая. Общие требования к организации и методам контроля качества \nГОСТ Р 54523—2011 Портовые гидротехнические сооружения. Правила обследования и монито­\nринга технического состояния\nСП 28.13330.2017 «СНиП 2.03.11—85 Защита строительных конструкций от коррозии»\nСП 31.13330.2012 «СНиП 2.04.02—84* Водоснабжение. Наружные сети и сооружения» (с измене­\nниями №1,2)\nСП 32.13330.2012 «СНиП 2.04.03—85 Канализация. Наружные сети и сооружения» (с изменением\n№ 1)\nИздание официальное\n1"
        },
        {
            "page": 6,
            "page_content": "СП 377.1325800.2017\nСП 38.13330.2012 «СНиП 2.06.04—82* Нагрузки и воздействия на гидротехнические сооружения \n(волновые ледовые и от судов)»\nСП 62.13330.2011 «СНиП 42-01—2002 Газораспределительные системы» (с изменениями №1,2)\nСП 68.13330.2017 «СНиП 3.01.04—87 Приемка в эксплуатацию законченных строительством объ­\nектов. Основные положения»\nПримечание — При пользовании настоящим сводом правил целесообразно проверить действие ссы­\nлочных стандартов (сводов правил) в информационной системе общего пользования — на официальном сайте \nфедерального органа исполнительной власти в сфере стандартизации в сети Интернет или по ежегодному инфор­\nмационному указателю «Национальные стандарты», который опубликован по состоянию на 1 января текущего года, \nи по выпускам ежемесячного информационного указателя «Национальные стандарты» за текущий год. Если заме­\nнен ссылочный документ, на который дана недатированная ссылка, то рекомендуется использовать действующую \nверсию этого документа с учетом всех внесенных в данную версию изменений. Если заменен ссылочный документ, \nна который дана датированная ссылка, то рекомендуется использовать версию этого документа с указанным выше \nгодом утверждения (принятия). Если после утверждения настоящего свода правил в ссылочный документ, на ко­\nторый дана датированная ссылка, внесено изменение, затрагивающее положение, на которое дана ссылка, то это \nположение рекомендуется применять без учета данного изменения. Если ссылочный документ отменен без замены, \nто положение, в котором дана ссылка на него, рекомендуется применять в части, не затрагивающей эту ссылку. Све­\nдения о действии сводов правил целесообразно проверить в Федеральном информационном фонде стандартов.\n3 Термины и определения\nВ настоящем своде правил применены термины по ГОСТ Р 54523, ГОСТ 27751, а также следую­\nщие термины с соответствующими определениями:\n3.1 аппарель (элемент конструкции судна или причала) (здесь): Пологая платформа (насыпь \nна берегу), предназначенная для въезда транспортных средств и передвижения пешеходов с причаль­\nного сооружения (берега) на паромную переправу или наплавной мост, а также их съезда и схода об­\nратно.\n3.2 контроль технического состояния сооружения: Мероприятия, включающие проведение из­\nмерений, испытаний, проверки одной или нескольких характеристик сооружения и их сравнение с уста­\nновленными требованиями с целью определения соответствия.\n3.3 моральный износ (здесь): Утрата сооружением возможности удовлетворения новым возрос­\nшим эксплуатационным требованиям при сохранении своих параметров, установленных проектом.\n3.4 наплавной мост: Мост на плавучих опорах, представляющий собой искусственное сооруже­\nние, предназначенное для движения транспортных средств и пешеходов в местах пересечения автомо­\nбильными дорогами водных преград.\n3.5 обследование конструкций: Комплекс работ по сбору, обработке и систематизации данных \nо техническом состоянии конструкции с целью их анализа и оценки.\n3.6 объекты инфраструктуры морского порта: Портовые гидротехнические сооружения, вну­\nтренние рейды, якорные стоянки, доки, буксиры, ледоколы и иные суда портового флота, средства \nнавигационного оборудования и другие объекты навигационно-гидрографического обеспечения мор­\nских путей, системы управления движением судов, информационные системы, перегрузочное обору­\nдование, железнодорожные и автомобильные подъездные пути, линии связи, устройства тепло-, газо-, \nводо- и электроснабжения, иные устройства, оборудование, инженерные коммуникации, склады, иные \nздания, строения, сооружения, расположенные на территории и (или) акватории морского порта и пред­\nназначенные для обеспечения безопасности мореплавания, оказания услуг в морском порту, обеспече­\nния в морском порту государственного контроля (надзора).\n3.7 осмотры зданий и сооружений: Контроль за техническим состоянием зданий и сооружений, \nосуществляемый путем систематических осмотров с использованием средств технической диагностики.\nПримечание — Осмотры подразделяются на плановые, которые делятся на общие и частичные и про­\nводятся специально назначенными комиссиями, и внеплановые.\n3.8 паром: Судно, предназначенное для регулярной перевозки автотранспортных средств, грузов \nи пассажиров через участок водного пути в местах его пересечения автомобильной дорогой.\n3.9 паромная переправа: Участок водного пути с причальными сооружениями и курсирующими \nна нем специализированными судами-паромами в местах его пересечения автомобильной дорогой.\n3.10 территория морского порта: Земельный(ые) участок(ки), не покрытый(ые) поверхностными \nводами, в границах морского порта, в том числе искусственно созданный(ые) земельный(ые) участок(ки).\n2"
        },
        {
            "page": 7,
            "page_content": "СП 377.1325800.2017\n4 Общие положения\n4.1 Эксплуатация зданий, сооружений, акваторий и судоходных каналов портов и судоремонтных \nзаводов (далее — портовых сооружений и акваторий предприятий) должна обеспечивать сохранение \nих эксплуатационных характеристик в течение расчетного срока службы при наиболее эффективном \nиспользовании и соблюдении требований безопасности.\nПри соблюдении требований безопасности морского транспорта и объектов его инфраструктуры \nследует руководствоваться [4].\n4.2 Эксплуатацию судоподъемных сооружений (слипы, плавучие и сухие доки и т. п.) следует осу­\nществлять в соответствии с требованиями ГОСТ Р 54523. Требования по эксплуатации судоподъемных \nсооружений приведены в [15].\n4.3 При эксплуатации железнодорожных путей, расположенных на территории предприятия (заво­\nда) и находящихся на его балансе, следует руководствоваться [7].\n4.4 При технической эксплуатации сетей и сооружений водоснабжения на предприятии следует \nруководствоваться требованиями ГОСТ 12.3.006, ГОСТ 2761, ГОСТ Р 51232, СП 31.13330.\n4.5 При технической эксплуатации сетей и сооружений канализации на предприятии следует ру­\nководствоваться требованиями ГОСТ 12.3.006, СП 32.13330, СП 68.13330.\n4.6 При технической эксплуатации сетей и сооружений теплоснабжения на предприятии следует \nруководствоваться требованиями СП 62.13330.\n4.7 При технической эксплуатации газораспределительных сетей и сооружений на них, а также \nкомпрессорных станций на предприятии следует руководствоваться требованиями [6].\n4.8 При технической эксплуатации сетей и сооружений электроснабжения и электроосвещения на \nпредприятии следует руководствоваться [8].\n4.9 Требования по технической эксплуатации сетей и сооружений связи на предприятии приведе­\nны в [17].\n4.10 Техническую эксплуатацию объектов предприятий следует осуществлять в соответствии с \nтребованиями к охране окружающей среды.\n4.11 Портовые сооружения и акватории в замерзающих портах следует эксплуатировать в соот­\nветствии с указаниями настоящего свода правил.\n4.12 Эксплуатация портовых сооружений включает: установление режима эксплуатации соору­\nжений и надзор за его соблюдением; наблюдение за сооружениями и постоянное поддержание их в \nработоспособном техническом состоянии; проведение мероприятий по противокоррозионной защите \nконструкций сооружений; вскрытие резервов несущей способности сооружений с целью повышения \nэффективности их использования (увеличение нагрузок, глубин, пропускной способности, улучшение \nусловий эксплуатации и т. д.) с минимальными затратами на их усиление и переустройство; перспек­\nтивное планирование и проектирование реконструкции и ремонта важнейших сооружений в сочетании \nи увязке с новым строительством; текущий и капитальный ремонт сооружений; составление и ведение \nпаспорта портового гидротехнического сооружения в соответствии с ГОСТ Р 54523.\n4.13 Мероприятия по противокоррозионной защите конструкций сооружений следует проводить в \nсоответствии с СП 28.13330.\n4.14 Нагрузки волновые, ледовые и от судов на портовые гидротехнические сооружения следует \nопределять по СП 38.13330.\n4.15 Взаимодействие между производственными структурными подразделениями предприятия \n(завода), участвующими в технической эксплуатации портовых сооружений и акваторий, следует уста­\nнавливать в соответствии со схемой управления предприятием (заводом).\n4.16 В процессе эксплуатации портовых сооружений и акваторий следует обеспечивать соответ­\nствие их состояния и режима эксплуатации требованиям действующих противопожарных и санитарных \nнорм и правил, а также требованиям охраны труда.\n4.17 Техническая эксплуатация временных сооружений, расположенных на территории предпри­\nятий, должна обеспечивать нормальные и безопасные условия работы в них.\n4.18 Техническая эксплуатация портовых сооружений, сданных предприятием в аренду, должна \nосуществляться арендаторами по договору аренды.\n4.19 Эксплуатирующими предприятиями (заводами) должны быть разработаны в зависимости от \nместных условий:\n- требования по предотвращению загрязнения территории предприятия, расположенных на ней \nпортовых сооружений, акватории предприятия, а также атмосферы в районе предприятия;\n- допускаемые нагрузки на причалы, крытые и открытые грузовые склады [16].\nз"
        },
        {
            "page": 8,
            "page_content": "СП 377.1325800.2017\n4.20 Программу обследований и мониторинга технического состояния портовых сооружений сле­\nдует разрабатывать в соответствии с ГОСТ Р 54523.\n4.21 Эксплуатация порта должна удовлетворять требованиям [1].\n4.22 На территории предприятий или на территории отдельных производственных перегрузоч­\nных комплексов (ППК), морвокзалов и других производственных структурных подразделений следует \nустанавливать транспаранты-указатели со схемами расположения основных причалов, складов, других \nобъектов, крановых и железнодорожных путей, дорог, проемов и пешеходных переходов. На схемах \nдолжны быть указаны значения допускаемых нагрузок.\n4.23 Для упрощения ориентации в порту и улучшения эксплуатации следует разработать нагляд­\nные пособия (иллюстрации, надписи и т. п.), которые должны быть вывешены или установлены в слу­\nжебных помещениях производственных структурных подразделений предприятий (заводов), а также \nв производственных и складских помещениях зданий и сооружений, на причалах, открытых грузовых \nскладах и на судах портового флота.\n4.24 При возникновении существенных изменений в условиях эксплуатации сооружения (измене­\nние глубин у гидротехнических сооружений, изменение технического состояния элементов конструкций \nсооружений и грунтов их основания и т. п.) режим эксплуатации в соответствии с требованиями [4], [5].\n4.25 Складировать грузы на железнодорожных и других транспортных путях, а также на колодцах \nинженерных сетей не допускается.\nКо всем колодцам должен быть обеспечен свободный подход, а к пожарным гидрантам — проезд.\nКрышки люков на колодцах инженерных сетей должны быть всегда плотно закрыты.\n4.26 Вывод из эксплуатации портовых сооружений, осуществляемый вследствие невозможности \nили нецелесообразности дальнейшего их использования по назначению или в случаях, когда создается \nугроза несчастных случаев с людьми или опасность аварии зданий, сооружений, судов, механизмов и \nоборудования, и в соответствии с требованиями [4] должен осуществлять собственник объекта.\nРешение о выводе сооружений из эксплуатации должно быть оформлено актом, утвержденным \nруководителем предприятия (завода), и доведено до сведения вышестоящей организации.\n4.27 Указания руководства по режиму эксплуатации портовых сооружений, а также по его измене­\nнию, обязательны для всех организаций, расположенных на территории предприятия (завода).\n4.28 Техническое состояние и режим эксплуатации портовых сооружений и акваторий должны \nопределяться путем регулярных технических осмотров, периодических технических осмотров, кон­\nтрольно-инспекторских обследований,внеочередных обследований.\nПериодичность регулярных технических осмотров различных групп сооружений и указания по их \nпроведению приведены в соответствующих разделах настоящего свода правил.\nРезультаты регулярных технических осмотров следует оформлять для основных групп сооружений.\nУказания по проведению периодических технических осмотров основных групп портовых соору­\nжений содержатся в соответствующих разделах настоящего свода правил.\nПериодические технические осмотры сооружений следует проводить не реже одного раза в год \nкомиссией под председательством главного инженера предприятия, назначаемого приказом по пред­\nприятию (заводу).\n4.29 Контрольно-инспекторские обследования включают комплекс работ по изучению состояния \nпортовых сооружений и всех основных конструктивных элементов с применением различного рода ин­\nструментов и аппаратуры, путем взятия и исследования проб материалов, испытаний всего сооружения \nили его частей и т. п.\nКонтрольно-инспекторские обследования сооружений в соответствии с требованиями [4], [5] \nдолжны осуществляться аккредитованным испытательным центром (лабораторией).\nПериодичность проведения контрольно-инспекторских обследований сооружений должна состав­\nлять пять лет.\n4.30 Внеочередные обследования устанавливают техническое состояние сооружений в тех случа­\nях, когда они подвергались воздействиям, выходящим за пределы нормальных условий эксплуатации, \nв случаях обнаружения аварий или значительных повреждений, а также при возникновении необходи­\nмости использования сооружений по другому назначению или при режимах эксплуатации, отличающих­\nся от установленных ранее.\nВнеочередные обследования следует проводить в соответствии с требованиями [4], [5] аккредито­\nванным испытательным центром (лабораторией).\n4.31 Для проведения геодезических наблюдений за плановым и высотным положением основных со­\nоружений на территории предприятия (завода) должны быть установлены знаки опорной геодезической\n4"
        },
        {
            "page": 9,
            "page_content": "СП 377.1325800.2017\nсети (реперы), отметки которой должны быть связаны с общегосударственной системой отметок, а на \nсамих сооружениях — знаки наблюдательной геодезической сети (наблюдательные марки).\n4.32 Знаки опорной и наблюдательной геодезических сетей следует предохранять от повреждений \nи коррозии. Запрещается укладывать на знаки опорной сети грузы, швартовать за них шлюпки и катера.\nГоловки реперов и марок следует покрывать защитной смазкой, а кожухи и крышки окрашивать.\n4.33 Для определения отклонений фактического уровня акватории от нуля глубин на территории \nпорта должен быть установлен мареограф с выносными репитерами в помещениях службы портового \nнадзора и главной диспетчерской или водомерный пост.\nВ случае, когда устройство мареографа или водомерного поста невозможно или нецелесообраз­\nно, данные для регулярного определения фактического уровня нуля глубин необходимо получать от \nрасположенной вблизи поста государственной системы Росгидромет.\n4.34 В необходимых случаях для установления причин деформаций и мер по их ликвидации пред­\nприятию (заводу) совместно с проектной организацией следует выполнять работы по вскрытию соору­\nжений и их оснований (буровые работы, испытание сооружений опытными статическими нагрузками). \nРаботы должны выполняться аккредитованными испытательными центрами (лабораториями).\n4.35 В соответствии с ГОСТ Р 54523 по результатам первичного обследования сооружения со­\nставляется его паспорт. По результатам очередного, внеочередного или специального обследования \nсооружения, в случае изменения его паспортных характеристик, проводят соответствующую корректи­\nровку паспорта.\n4.36 Строительный контроль за капитальным ремонтом портовых сооружений должен осущест­\nвляться администрацией порта.\n4.37 Ремонтные дноуглубительные работы на акваториях и судоходных каналах предприятий \nдолжны выполняться бассейновыми управлениями морских путей в соответствии с указаниями насто­\nящего свода правил.\n4.38 На территории предприятий (заводов) запрещается проведение земляных работ без разре­\nшения главного инженера предприятия.\nЕсли по территории предприятия (завода) в районе предстоящих земляных работ проходят под­\nземные коммуникации сторонних организаций, ведение земляных работ должно быть согласовано ру­\nководством предприятия (завода) с руководителями указанных организаций в установленном порядке.\n4.39 Ответственность за техническое состояние и режим эксплуатации портовых сооружений и \nакваторий следует устанавливать в соответствии с настоящим сводом правил, положениями о произ­\nводственных структурных подразделениях предприятий (заводов).\n5 Охрана окружающей среды\n5.1 Территория, портовые сооружения и акватория предприятия, а также атмосфера в районе \nпредприятия (завода) должны содержаться в санитарном состоянии, отвечающем требованиям по ох­\nране окружающей среды.\n5.2 Во избежание засорения и загрязнения причальных сооружений на территорию причалов за­\nпрещается выливать нефтепродукты, выбрасывать золу, шлак, балласт, мусор, отбросы и т. п.\n5.3 При перегрузке сыпучих грузов необходимо принимать меры, предотвращающие их просыпа­\nние в акваторию порта.\n5.4 Слив нефтесодержащих и отработанных хозяйственно-бытовых вод с судов следует осущест­\nвлять в емкости специальных плавсредств. При наличии на причале приемных устройств загрязненные \nводы следует откачивать на береговые очистные сооружения. Различные отходы с судов следует сда­\nвать береговым службам для специальной обработки.\n5.5 Для предотвращения загрязнения и в целях очистки вод акватории предприятия и ее дна долж­\nны осуществляться следующие мероприятия:\n- обследования акватории, включающие наблюдения за чистотой поверхностных вод и дна, а так­\nже за химическими, бактериологическими и токсическими свойствами сточных вод, при этом в случае \nобнаружения недопустимого загрязнения незамедлительно должны быть приняты меры по его ликви­\nдации;\n- оборудование предприятий специальными стационарными и передвижными (аварийными) \nустройствами для локализации распространения по акватории пролитых нефтепродуктов и других жид­\nких грузов с учетом местных климатических условий;\n5"
        },
        {
            "page": 10,
            "page_content": "СП 377.1325800.2017\n- обеспечение предприятий специальными судами для сбора нефтесодержащих и отработанных \nхозяйственно-бытовых вод плавучими нефтемусоросборщиками для очистки поверхностных вод и за- \nчистными станциями;\n- организация береговых пунктов приема с судов различных отходов, нефтесодержащих и отра­\nботанных хозяйственно-бытовых вод.\n5.6 При обнаружении повышенного загрязнения вод, поступающих в его акваторию из выпусков \nгородской канализации и промышленных предприятий, следует немедленно проинформировать об \nэтом местные органы власти и одновременно принять срочные меры по локализации и ликвидации \nзагрязнения и его последствий.\nО любом загрязнении вод акватории предприятия сверх установленных норм должен быть состав­\nлен акт с указанием источника загрязнения.\n5.7 При проведении ремонтных дноуглубительных работ специальные исследования, связанные \nс охраной окружающей среды, а также химические анализы донного грунта и воды должна проводить \nпроектная организация.\n5.8 Заказчик или, по его поручению, строительная организация должны оборудовать береговые \nотвалы и поддерживать их в эксплуатационном состоянии в соответствии с требованиями органов ох­\nраны окружающей среды в течение всего периода проведения ремонтных дноуглубительных и рефу­\nлерных работ.\n5.9 При дноуглублении участков вблизи водозаборных устройств следует учитывать направление \nтечений и зону распространения облака мутности. В неблагоприятных случаях должен быть решен во­\nпрос о том, чтобы водоснабжение объектов, пользующихся водозаборным устройством в период про­\nведения ремонтных дноуглубительных работ, осуществлялось из другого источника.\n5.10 При проведении ремонтных дноуглубительных работ в акватории предприятия, а также при \nотвозке извлеченного грунта на подводный отвал должны выполняться требования по охране окружаю­\nщей среды и рационально использоваться места, отведенные для отвала.\n6 Портовые гидротехнические сооружения\n6.1 Режим эксплуатации\n6.1.1 Режим эксплуатации портовых гидротехнических сооружений (оградительных, причальных, \nберегоукрепительных, а также гидротехнических сооружений паромных переправ и судоремонтных за­\nводов) представляет совокупность условий и требований, которые следует выполнять как работникам \nпредприятий, так и экипажам судов, использующих сооружение.\n6.1.2 Режим эксплуатации портовых гидротехнических сооружений следует устанавливать в за­\nвисимости от их основного назначения.\nВнесение изменений в установленный режим эксплуатации портовых гидротехнических со­\nоружений должен проводить аккредитованный испытательный центр на основании результатов \nобследований объекта инфраструктуры морского транспорта и данных об изменении условий их \nэксплуатации.\n6.1.3 Техническая эксплуатация портовых гидротехнических сооружений должна обеспечивать: \nнормальные условия для плавания, стоянки и обработки судов; сохранность и повышение долговеч­\nности сооружений при их взаимодействии с судами, при работе оборудования и транспорта, при скла­\nдировании грузов, а также при воздействии гидрометеорологических факторов; снижение эксплуатаци­\nонных расходов.\n6.1.4 Глубину у кордона или у подошвы портовых гидротехнических сооружений следует устанав­\nливать в соответствии с классификацией глубин. Классификация глубин приведена в [16].\n6.1.5 Смещения и деформации гидротехнических сооружений за период их эксплуатации не долж­\nны превышать значений, установленных проектом.\n6.1.6 Все причальные сооружения следует эксплуатировать при строгом соблюдении установлен­\nных для них норм эксплуатационных нагрузок, которые указаны в паспортах.\nУвеличение нагрузок на причальные сооружения сверх установленных норм не допускается.\nПересмотр норм эксплуатационных нагрузок следует проводить в соответствии с [4].\nНормы эксплуатационных нагрузок следует устанавливать для каждого участка причального \nфронта, отличающегося по конструкции или по техническому состоянию конструктивных элементов, \nнезависимо от объединения ряда участков в один причал по эксплуатационной нумерации.\n6"
        },
        {
            "page": 11,
            "page_content": "СП 377.1325800.2017\n6.1.7 При изменении условий эксплуатации причалов и их технического состояния должны быть \nпроведены поверочные расчеты сооружений, результаты которых должны учитываться при назначении \nнового режима эксплуатации.\n6.1.8 Если значения нагрузок от складирования грузов превышают значения допускаемых нагру­\nзок [16], тяжеловесные грузы и оборудование следует устанавливать на распределительные платфор­\nмы специальной конструкции.\n6.1.9 Границы причалов с различными глубинами у кордона и различной несущей способностью \nдолжны быть обозначены на месте.\nСхемы нагрузок на причальные сооружения следует вывешивать на видном месте на причалах, \nв служебных помещениях, в которых находятся работники, связанные с эксплуатацией причальных со­\nоружений.\n6.1.10 Рейдовые причальные сооружения (швартовные палы и бочки) необходимо эксплуатиро­\nвать при строгом соблюдении установленных для них норм нагрузок от швартующихся судов. Указан­\nные рейдовые причальные сооружения рекомендуется также использовать при задержке судов на вну­\nтреннем рейде, а также при неблагоприятных погодных условиях.\n6.1.11 Для каждого причала приказом по предприятию (заводу) должны быть установлены глу­\nбины и допускаемая осадка швартующихся судов, условия подхода и швартовки, безопасной стоянки, \nперестановки судов, меры предупреждения повреждений гидротехнических сооружений судами.\n6.1.12 Для обеспечения безопасной швартовки судов и сохранности причальных сооружений \nдолжны быть удовлетворены следующие требования:\n- швартовные и отбойные устройства причального сооружения должны находиться в исправном \nтехническом состоянии на всем протяжении причалов и соответствовать по своим характеристикам \nсудам, швартующимся к причалам;\n- фактический запас свободной длины причалов при швартовке судна не должен быть менее нор­\nмативного запаса, зависящего от длины швартующегося судна;\n- нормальные составляющие скоростей подхода судов к причалам при их швартовке следует \nустанавливать по СП 38.13330 в зависимости от водоизмещения судов.\nПри перешвартовке судов, то есть при переходе судна от одного причала к другому с отходом от \nлицевой стенки причалов, также не допускается превышение указанных нормальных составляющих \nскоростей подхода судов к причалу.\nНе допускается швартовка судов к сооружениям, на которых отбойные устройства не навешены \nили повреждены.\n6.1.13 Перед подходом судна к причалу выступающие за борт предметы должны быть заблаговре­\nменно убраны и закреплены в таком положении, чтобы они не могли повредить причалы и находящиеся \nна них устройства и перегрузочное оборудование.\n6.1.14 Для предотвращения повреждений судов, портовых сооружений и несчастных случаев с \nлюдьми дежурный диспетчер предприятия (завода) обязан заранее обеспечить подготовку причала к \nприему судна. В случае необходимости перегрузочное оборудование должно быть перемещено на уча­\nсток причала, где оно не подвергается опасности повреждения.\nДежурный службы портового надзора должен проверять готовность причала для швартовки.\nТребования к швартовке судов в ледовых условиях приведены в [16].\n6.1.15 При приеме у причалов накатных судов (типа Ро-Ро) опускание аппарели на причал раз­\nрешается только в местах, специально для этого предназначенных и снабженных соответствующими \nнадписями. Габариты зоны укладки аппарели должны быть обозначены на причале четкими линиями \nкраской или другим способом.\n6.1.16 Суда с носовыми бульбами должны подходить к причалам при условии соблюдения следу­\nющих требований:\n- судно должно подводиться к причалу с помощью буксиров;\n- при касании причала корпусом судна должно быть исключено соприкосновение бульба с при­\nчалом.\n6.1.17 Швартовку судов следует проводить швартовными канатами только за швартовные устрой­\nства. Запрещается подача на швартовные устройства якорных цепей.\nШвартовку судов после получения штормового предупреждения следует проводить за штормовые \nшвартовные устройства.\nШвартовка за отбойные устройства, а также за какие-либо части сооружения, не предназначен­\nные специально для швартовки, запрещается.\n7"
        },
        {
            "page": 12,
            "page_content": "СП 377.1325800.2017\n6.1.18 В порту, при швартовке, стоянке и проведении погрузочно-разгрузочных работ у причалов \nсвайного типа не следует допускать крена судна на внешнюю сторону ввиду опасности повреждения \nсудна или подводной части причала; у причалов гравитационного типа не следует допускать крена \nсудна на внешнюю сторону более 5°. На судоремонтном заводе (СРЗ) при швартовке ремонтируемых \nсудов у причалов может быть допущен больший их крен на внешнюю сторону. Значение угла крена в \nэтом случае следует определять, исходя из условия недопустимости касания бортом судна лицевой \nстенки причала.\nСоблюдение указанного условия должно обеспечиваться за счет соответствующего выноса ого­\nловка причала, а также отбойных устройств.\n6.1.19 При отходе от причала суда должны работать машиной самым малым ходом, пока борт \nсудна не будет на расстоянии не менее 10 м от набережной.\nКрупнотоннажные суда, отходящие от причалов порта, не должны маневрировать своими маши­\nнами вблизи причалов, а обязаны, используя буксирные суда, отходить в районы акватории, где манев­\nрирование не будет создавать опасности повреждения других судов, гидротехнических сооружений и \nразмыва дна у сооружений.\nКатегорически запрещается проводить швартовные испытания судов, связанные с работой греб­\nных винтов, у гидротехнических сооружений, не предназначенных для этой цели.\nПри стоянке судна непосредственно у причала допускается для прогрева машины работа гребны­\nми винтами на самых малых оборотах.\nНеобходимость использования буксиров при подходе судов к причалам и отходе от них устанав­\nливается [1] в зависимости от тоннажа судна и конструкции причальных сооружений.\n6.1.20 Капитан судна, повредившего гидротехническое сооружение, обязан немедленно сообщить \nоб этом капитану порта.\n6.1.21 Для обеспечения необходимых условий швартовки судов и выполнения других операций у \nкордона причальных сооружений запрещается складирование грузов в пределах полосы шириной от \nлинии кордона не менее 2 м.\n6.1.22 Причальные сооружения должны быть оборудованы по кордону колесоотбойными бру­\nсьями.\nНа причалах, предназначенных для приема накатных судов (типа Ро-Ро), участок установки ап­\nпарели должен быть оборудован съемным колесоотбойным брусом. Колесоотбойные брусья должны \nпостоянно находиться в исправном состоянии и систематически очищаться от мусора, льда и снега.\n6.1.23 Через трубопроводы и другие коммуникации, выступающие над поверхностью причала, \nдолжны быть установлены переходные мостики для безопасного прохода людей.\n6.1.24 При эксплуатации причалов пользование сварочными аппаратами, паяльными лампами и \nдругими огнедействующими приборами на сооружениях допускается только после соблюдения требо­\nваний [3].\n6.1.25 Эксплуатацию причалов для приема наливных грузов следует проводить в соответствии \nс технологическими требованиями специальных инструкций по эксплуатации, разрабатываемых для \nтаких причалов на основании действующих нормативных документов с учетом особенностей работ на \nкаждом причале.\n6.1.26 Профиль оградительных и берегоукрепительных сооружений должен поддерживаться в те­\nчение всего периода их эксплуатации в проектном положении.\n6.1.27 Запрещается складирование массивов, железобетонных изделий и других грузов на огра­\nдительных и берегоукрепительных сооружениях без проверки несущей способности последних и уста­\nновления допустимой на них нагрузки.\n6.1.28 Для берегоукрепительных сооружений, к которым непосредственно примыкают открытые \nгрузовые склады, должны быть установлены нормы эксплуатационных нагрузок в прикордонной по­\nлосе [16].\n6.1.29 Откосы берегоукрепительных сооружений, не имеющие одежды, необходимо предохранять \nот размыва путем посадки растений, устройства упора или гибких покрытий и т. п.\n6.1.30 Складирование каких-либо предметов на откосах берегоукрепительных сооружений запре­\nщается.\n6.1.31 В каждом порту, имеющем внутренние и внешние рейды, должно быть установлено пре­\nдельное приближение к оградительным или берегоукрепительным сооружениям для судов, становя­\nщихся на якорь на рейде.\nМеста якорных стоянок на рейдах должны быть указаны на схематическом плане порта.\n8"
        },
        {
            "page": 13,
            "page_content": "СП 377.1325800.2017\n6.1.32 На портовых гидротехнических сооружениях, в местах выведения подводных кабелей и \nтрубопроводов на берег, должны быть установлены запрещающие знаки в соответствии с ГОСТ 26600.\n6.1.33 В тех случаях, когда гидротехнические сооружения или их отдельные элементы могут быть \nповреждены льдом, принимают охранные меры, приведенные в [16].\n6.1.34 Портовые гидротехнические сооружения должны быть выведены из эксплуатации в том \nслучае, когда наличие значительных повреждений или прогрессирующее развитие деформаций и раз­\nрушений резко ухудшает условия их эксплуатации.\n6.2 Техническое обслуживание\n6.2.1 Техническое обслуживание портовых гидротехнических сооружений должно включать: рабо­\nты по поддержанию в исправности швартовых и отбойных устройств, дренажных систем и т. п., околку \nльда около сооружений; очистку откосов берегоукрепительных сооружений от загрязнений, устранение \nмелких повреждений и дефектов надводной части сооружений, работы по поддержанию чистоты и по­\nрядка на причалах, в том числе очистку причалов от мусора, снега и льда и др., а также наблюдения, \nобеспечивающие контроль за установленным режимом эксплуатации и техническим состоянием со­\nоружений.\n6.2.2 Работы по очистке дна и другие подводные работы, связанные с техническим обслуживани­\nем причалов, должны проводиться специализированными организациями.\n6.2.3 В случае если швартовные и отбойные устройства в процессе эксплуатации причальных \nсооружений получили повреждения, немедленно должны быть приняты меры по устранению этих по­\nвреждений.\nНа предприятии для проведения ремонта этих устройств следует иметь неснижаемый запас тумб, \nкнехтов, рымов, а также деталей, отбойных устройств или их готовых секций.\n6.2.4 Троллейные каналы и каналы электрических кабелей в составе портовых гидротехнических \nсооружений должны регулярно очищаться от мусора, а в зимний период — от снега и льда.\n6.2.5 При возникновении деформаций откосов берегоукрепительных сооружений следует немед­\nленно принять меры по восстановлению профиля откосов и их закреплению.\n6.2.6 Все случаи превышения эксплуатационных нагрузок сверх установленных норм, а также по­\nвреждений портовых гидротехнических сооружений, их частей и элементов, произошедшие вследствие \nнарушения режима их эксплуатации, следует оформлять двусторонними актами.\n6.2.7 Контрольно-инспекторские обследования портовых гидротехнических сооружений следует \nпроводить в зависимости от состояния сооружений, условий их эксплуатации.\nСроки и программа проведения контрольно-инспекторских обследований гидротехнических со­\nоружений предприятий должны разрабатываться в соответствии с требованиями [4].\n6.2.8 При контрольно-инспекторских обследованиях особое внимание следует обращать на при­\nзнаки возможного нарушения общей устойчивости сооружений (сдвиг сооружения в сторону акватории \nили наклон верхней части сооружения в сторону территории, просадка территории за сооружением, \nвыпучивание дна перед ним).\n6.2.9 В отчете по результатам контрольно-инспекторских обследований должно быть проведено \nсопоставление значений смещений и деформаций портовых гидротехнических сооружений, установ­\nленных в результате наблюдений с использованием средств измерений, и их предельно допустимых \nзначений.\nЗначения предельно допустимых смещений и деформаций портовых гидротехнических сооруже­\nний за период их эксплуатации приведены в [16].\nПри необходимости к отчету должны быть приложены поверочные расчеты прочности и устойчиво­\nсти сооружения в целом и отдельных его элементов, выполненные для конкретных условий эксплуатации.\nОсновные результаты контрольно-инспекторских обследований, содержащие общую оценку тех­\nнического состояния обследованных сооружений и в необходимых случаях указания по их ремонту или \nпереустройству, следует вносить в паспорта сооружений.\n6.2.10 Наблюдения за состоянием профиля постели и дна у портовых гидротехнических сооруже­\nний следует проводить путем промера глубин.\n6.2.11 Обследование подводной части гидротехнических сооружений должно проводиться водо­\nлазами или с использованием дистанционно-управляемых подводных аппаратов.\nПрограмма проведения подводных обследований должна предусматривать выполнение следу­\nющих видов работ: визуального осмотра сооружения, определения размеров объектов наблюдения\n9"
        },
        {
            "page": 14,
            "page_content": "СП 377.1325800.2017\nи технического состояния материалов конструкций с использованием средств измерений, получения \nфотодокументации подводных съемок.\n6.2.12 Внеочередные обследования причальных сооружений следует проводить в случае обна­\nружения их смещений, деформаций или повреждений, значения которых превосходят предельно до­\nпустимые, а также в случае повышения эксплуатационных нагрузок на них сверх установленных норм.\nВнеочередные обследования оградительных и берегоукрепительных сооружений следует произ­\nводить после сильных штормов с волнением более пяти баллов.\n6.2.13 В результате внеочередных обследований должна быть установлена возможность даль­\nнейшей эксплуатации сооружений до проведения ремонтных или восстановительных работ, перечень \nпервоочередных ремонтных работ, которые необходимо провести для ввода сооружений в действие, и \nперечень работ, которые должны быть включены в план годовых ремонтных работ, с указанием объема \nи сроков их выполнения.\n6.3 Ремонт\n6.3.1 Текущий и капитальный ремонты портовых гидротехнических сооружений и оборудования \nрейдовых причалов, планируемые по результатам регулярных и периодических технических осмотров, \nдолжны проводиться организацией, на которую это возложено договором, а при отсутствии договора — \nсобственником портового сооружения.\n6.3.2 Капитальный ремонт портовых гидротехнических сооружений следует выполнять по проекту, \nразработанному с учетом результатов технического обследования объекта аккредитованным испыта­\nтельным центром.\n6.3.3 При капитальном ремонте портовых гидротехнических сооружений, которые имеют мораль­\nный износ, следует предусматривать их переустройство с целью повышения эксплуатационных харак­\nтеристик сооружений (повышение норм эксплуатационных нагрузок, глубин и т. п.).\n7 Крытые склады\n7.1 Режим эксплуатации\n7.1.1 Техническая эксплуатация крытых складов общего назначения должна обеспечивать: надеж­\nную защиту складируемых грузов, материалов и оборудования от внешних воздействий (снега, дождя, \nветра и др.) при их хранении; сохранность и долговечность складов и их конструктивных элементов при \nустановленном режиме эксплуатации складов; нормальные условия работы персонала, внутрисклад- \nской механизации и внутри портового транспорта; соблюдение противопожарных и санитарных требо­\nваний, а также требований техники безопасности.\n7.1.2 Для каждого крытого склада должен быть установлен режим эксплуатации с нормами допу­\nскаемых нагрузок на полы и перекрытия и составлены схемы загрузки полов и перекрытий. На схемах \nзагрузки должны быть показаны противопожарные проходы и постоянные технологические проезды.\nДля крытых складов насыпных грузов дополнительно должна устанавливаться допускаемая высо­\nта штабеля у стен и колонн, соответствующая допускаемым горизонтальным нагрузкам от распорного \nдавления груза данного вида.\nПревышение установленных норм нагрузок на полы, перекрытия и стены складов запрещается.\nНормы допускаемых нагрузок для крытых складов следует периодически пересматривать с уче­\nтом фактического технического состояния основных конструктивных элементов каждого склада.\nВ каждом крытом складе должны быть вывешены на видном месте наглядно выполненные табли­\nцы, содержащие сведения о допускаемых нагрузках на полы и перекрытия склада, а также при необхо­\nдимости схемы загрузки и схемы движения транспортных средств.\n7.1.3 Механическое оборудование крытых складов (ворота, раздвижные крыши, лифты, конвейе­\nры, монорельсы, тельферы и т. п.) должно иметь паспорта и инструкции по эксплуатации оборудования.\n7.1.4 Установка в крытых складах механического оборудования, не предусмотренного проектом, \nбез поверочных расчетов не допускается.\n7.1.5 Внутри крытых складов разрешается работа только тех машин внутрипортового (внутри­\nзаводского) транспорта, которые предусмотрены технологическими картами, составленными в со­\nответствии с установленными нормами допускаемых нагрузок на полы и перекрытия складов и с \nучетом требования, чтобы максимальные скорости этих машин не превышали предельно допустимых \nзначений.\n1 0"
        },
        {
            "page": 15,
            "page_content": "СП 377.1325800.2017\n7.1.6 Движение транспорта в крытых складах должно быть организовано таким образом, чтобы \nисключалась опасность нанесения повреждений конструктивным элементам складов. При работе на \nбалконах и террасах многоэтажных складов расстояние между погрузчиками и ограждением должно \nсоставлять не менее 1,0 м.\n7.1.7 В крытых складах у проемов ворот в створе вертикальных стоек с внутренней и с наружной \nстороны должны быть установлены охранные столбики, окрашенные в легкоразличимый цвет в соот­\nветствии с ГОСТ 12.4.026.\n7.1.8 Режим эксплуатации складов при скорости ветра, превышающей 20 м/с, должен устанавли­\nваться предприятием (заводом) с учетом местных условий. В паспорте склада и настенных таблицах \nдопускаемых нагрузок должна приводиться скорость ветра, при которой ворота в зависимости от рас­\nположения их относительно направления ветра следует держать закрытыми.\n7.1.9 Противопожарные проходы в крытых складах должны соответствовать требованиям [3].\nПожарные проходы и постоянные технологические проезды на складах должны быть всегда сво­\nбодны от грузов.\n7.1.10 Грузы, которые могут причинить механические повреждения полам крытых складов, долж­\nны складироваться только на подкладках. Не допускается складирование грузов, агрессивных по от­\nношению к бетону или асфальтобетону полов, навалом и в неисправной таре.\n7.1.11 В крытых складах следует поддерживать чистоту и порядок. Сепарация, поддоны и дру­\nгой складской инвентарь должны аккуратно складываться и храниться в специально отведенных \nместах.\n7.1.12 0  повреждениях, нанесенных конструктивным элементам крытого склада в процессе пере­\nгрузочных работ, должностные лица, ответственные за состояние крытого склада, обязаны доклады­\nвать руководителям предприятий (заводов).\n7.1.13 При появлении опасных деформаций или разрушений основных конструктивных элементов \nкрытого склада, создающих угрозу аварии (обрушения), склад должен быть полностью или частично \nвыведен из эксплуатации.\n7.1.14 Режим эксплуатации крытых складов, входящих в состав специализированных перегрузоч­\nных комплексов, а также складов с раскрывающейся крышей и складов, в которых перегружаются гру­\nзы, агрессивно действующие на их конструктивные элементы, должен устанавливаться инструкциями, \nразрабатываемыми проектной организацией, и утверждаться руководством порта.\n7.1.15 Крытые склады должны быть обозначены хорошо различимыми номерами. Все ворота \nскладов должны быть также пронумерованы и обозначены.\n7.2 Техническое обслуживание\n7.2.1 Техническое обслуживание крытых складов должно включать систематические наблюдения \nза техническим состоянием складов и за установленным режимом их эксплуатации, а также работы по \nподдержанию складов в чистоте и порядке.\n7.2.2 При техническом обслуживании крытых складов путем систематических наблюдений долж­\nны быть обеспечены:\n- контроль за техническим состоянием складов и их конструктивных элементов, а также за уста­\nновленным режимом эксплуатации складов;\n- контроль за соответствием технического состояния противопожарного оснащения складов;\n- контроль за соответствием технического состояния складов и внутрискладского оборудования \nтребованиям санитарных норм и техники безопасности;\n- определение видов и объемов ремонтных работ.\n7.2.3 Наблюдения за состоянием крытых складов должны включать регулярные технические ос­\nмотры, периодические технические осмотры, специальные наблюдения с использованием средств из­\nмерений, внеочередные обследования.\n7.2.4 Периодические технические осмотры крытых складов должны осуществляться комиссией, \nорганизуемой на предприятии. Результаты периодических технических осмотров складов следует \nоформлять в виде отчетов и хранить совместно с паспортами складов.\n7.2.5 Наблюдения за техническим состоянием крытых складов с использованием средств изме­\nрений следует проводить: в начальный период эксплуатации складов, расположенных на просадочных \nгрунтах и грунтах большой сжимаемости до стабилизации осадок, а также в тех случаях, когда замече­\nны деформации основных конструктивных элементов складов.\n11"
        },
        {
            "page": 16,
            "page_content": "СП 377.1325800.2017\nПеречень сооружений, подлежащих наблюдениям с использованием средств измерений, их пе­\nриодичность и программа наблюдений должны разрабатываться предприятием (заводом) совместно с \nпроектной организацией.\n7.2.6 При обнаружении трещин в конструктивных элементах складов на них должны немедленно \nустанавливаться гипсовые или другие марки — маяки.\n7.2.7 Внеочередные обследования следует проводить в случаях появления опасных деформаций \nскладов и их основных конструктивных элементов, после обнаружения перегрузки полов и перекрытий \nсверх нормы допускаемой нагрузки, после значительных повреждений складских сооружений, получен­\nных в результате стихийных воздействий, а также при необходимости изменения условий эксплуатации.\nВнеочередные обследования должны проводиться комиссией, назначаемой начальником порта \nили руководителем предприятия (завода), с участием в необходимых случаях представителей проект­\nной организации.\n7.2.8 О случаях превышения норм допускаемых нагрузок на полы, перекрытия и стены крытых \nскладов работники, проводящие технический осмотр, обязаны немедленно сообщить главному инже­\nнеру предприятия (завода). В этих случаях должны быть немедленно приняты меры по приведению \nнагрузок в соответствие с допускаемыми.\n7.2.9 Кровля крытых складов не должна иметь протечек.\nОбнаруженные протечки кровли следует немедленно устранять.\n7.2.10 В зимний период кровли всех крытых складов должны регулярно очищаться от снега.\nОчистку крыш от снега следует проводить в обязательном порядке сразу же после больших сне­\nгопадов и в период, предшествующий весеннему таянию.\n7.2.11 Остекленные проемы крытых складов должны находиться в исправном состоянии, причем \nобнаруженные повреждения следует немедленно устранять.\n7.2.12 Полы крытых складов должны постоянно находиться в исправном состоянии, обеспечива­\nющем нормальную работу внутрипортового (внутризаводского) и внутрискладского транспорта и без­\nопасность людей.\nВызванные дефекты полов следует немедленно устранять.\n7.2.13 Системы пожарного водоснабжения в крытых складах должны периодически проверяться \nи соответствовать требованиям [3]. Периодичность проверок должна устанавливаться в зависимости \nот местных условий распоряжением главного инженера предприятия, согласованного с ответственным \nподразделением по пожарной безопасности.\nВ неотапливаемых складах системы сухотрубного пожарного водоснабжения при наступлении \nзимнего периода должны опорожняться во избежание размораживания труб. Опорожнение систем по­\nжарного водоснабжения и наполнение их с наступлением теплого периода должны проводиться каж­\nдый раз в соответствии со специальным распоряжением по порту или предприятию (заводу). После \nиспользования системы в зимний период она должна быть немедленно опорожнена.\n7.2.14 На складах должен находиться в полной исправности и постоянной эксплуатационной го­\nтовности противопожарный инвентарь, укомплектованный в соответствии с [3]. К противопожарному \nоборудованию и инвентарю должен быть обеспечен свободный доступ.\n7.3 Ремонт\n7.3.1 Текущий и капитальный ремонты крытых складов, планируемые по результатам регулярных \nи периодических технических осмотров, должны выполняться строительно-монтажными организация­\nми на договорной основе.\n7.3.2 Капитальный ремонт крытых складов в зависимости от объема и характера работ должен \nвыполняться ремонтно-строительным подразделением предприятия или подрядной строительной ор­\nганизацией.\n7.3.3 Ремонт каждого крытого склада следует осуществлять по возможности без вывода его из \nэксплуатации при условии обеспечения безопасности работающих на складе и сохранности грузов.\n8 Открытые грузовые склады и дороги\n8.1 Режим эксплуатации\n8.1.1 Вся оперативная портовая территория или территория предприятия (завода), за исключени­\nем участков, занятых по проекту благоустройства зелеными насаждениями, должна иметь покрытия,\n12"
        },
        {
            "page": 17,
            "page_content": "СП 377.1325800.2017\nтип и конструкция которых (монолитные, цементобетонные, из сборных железобетонных плит или ас­\nфальтобетонные) определяются условиями эксплуатации.\n8.1.2 Открытые грузовые склады на территории предприятий должны использоваться для склади­\nрования грузов, материалов и оборудования, которым не требуется защита от атмосферных осадков и \nдругих воздействий внешней среды, а также для кратковременного складирования грузов, требующих \nзакрытого хранения, под временными укрытиями.\nДля каждого открытого грузового склада должны быть установлены и соблюдаться нормы допу­\nскаемых нагрузок.\n8.1.3 Дороги, проезды и вспомогательные площадки на территории предприятий должны обеспе­\nчивать движение всех видов безрельсового транспорта, а также проезд противопожарной техники ко \nвсем объектам хозяйства и судам, стоящим у причалов.\nПри эксплуатации дорог следует соблюдать установленную интенсивность движения транспорт­\nных средств.\n8.1.4 Техническая эксплуатация открытых грузовых складов и дорог должна обеспечивать: ис­\nправное техническое состояние, необходимое для производительной и безаварийной работы безрель­\nсового транспорта и сохранности грузов; необходимую долговечность; совершенствование и модерни­\nзацию покрытий с учетом возможности изменения предъявляемых к ним требований.\n8.1.5 На территории предприятий запрещается движение неисправного или перегруженного \nтранспорта, а также перемещение грузов и оборудования волоком без специальных приспособлений и \nподкладок, предохраняющих покрытия от повреждений.\nПросыпавшиеся на покрытие грузы следует немедленно удалять.\n8.1.6 Для обеспечения сохранности открытых грузовых складов и дорог должен быть предусмо­\nтрен своевременный и эффективный отвод талых и ливневых вод; ливневая канализация и дренажные \nустройства на территории должны находиться в полной исправности. Поверхностные водостоки в виде \nлотков и каналов должны быть свободны от груза.\nУклоны поверхности покрытий должны обеспечивать полный сброс воды в водоотводящие устрой­\nства.\n8.1.7 Схемы загрузки площади открытых грузовых складов порта и таблицы норм допускаемых \nнагрузок на указанной площади следует размещать на территории складов на транспарантах в местах, \nне мешающих движению транспортных средств и проведению погрузочно-разгрузочных работ.\n8.1.8 При складировании на асфальтобетонных покрытиях грузов, растворяющих асфальтобетон \n(минеральные масла, жидкое топливо, жиры и т. п.), следует тщательно следить за исправностью и \nгерметичностью тары, не допуская возникновения протечек. Покрытие асфальтобетоном территории \nоткрытых грузовых складов, предназначенных для хранения навалочных грузов, не допускается.\n8.1.9 Складирование на асфальтобетонных покрытиях грузов с выступающими частями, которые \nмогут вдавливаться в покрытие, допускается только при надежной защите последнего сепарацией (под­\nкладками). Работа грейферами на асфальтобетонном покрытии не допускается.\n8.1.10 Складирование на бетонных покрытиях химических грузов, разрушающих бетон, без тары \nили в неисправной таре не допускается.\n8.1.11 Размещение штабелей грузов на территории открытых грузовых складов должно удовлет­\nворять следующим требованиям:\n- расстояние от штабелей грузов до стен зданий или сооружений должно быть не менее противо­\nпожарных требований, в зависимости от вида грузов и степени огнестойкости зданий или сооружений;\n- технологические проезды между штабелями грузов, а также между штабелями и стенами зданий \nили сооружений должны иметь ширину, обеспечивающую безопасность людей, а также сохранность \nзданий или сооружений и грузов при работе транспортных и перегрузочных средств;\n- расстояния от штабелей грузов до проезжей части дорог не должны быть менее 1,5 м.\n8.1.12 На территории открытых грузовых складов, предназначенных для хранения контейнеров, \nдолжна быть проведена разметка мест установки контейнеров и низкорамных полуприцепов.\n8.1.13 Постоянные технологические проезды и пожарные проезды на открытых складских пло­\nщадках должны быть свободны от грузов.\n8.1.14 При погрузочно-разгрузочных работах сбрасывание груза со штабелей или транспортных \nсредств не допускается.\n8.1.15 Движение машин на гусеничном ходу по дорогам и площадкам с асфальтобетонными по­\nкрытиями не допускается. Эти машины по асфальтобетонным покрытиям следует транспортировать\n13"
        },
        {
            "page": 18,
            "page_content": "СП 377.1325800.2017\nна трейлерах. По дорогам и площадкам с цементобетонным покрытием разрешается движение машин \nна гусеничном ходу только в случаях, когда они имеют плоские треки без выступающих частей.\n8.1.16 Пешеходные переходы через транспортные магистрали должны быть размечены краской \nна покрытиях. Ширина линий разметки 10—15 см.\n8.1.17 На территории открытых грузовых складов, предназначенных для хранения навалочных \nгрузов, следует устанавливать габаритные стенки, предотвращающие просыпание груза за габариты \nсклада в сторону крановых и железнодорожных путей, а также технологических и пожарных проездов.\n8.1.18 Скорость движения транспортных средств по территории предприятия (завода) должна \nустанавливаться приказом начальника порта (руководителем предприятия).\n8.1.19 Все препятствия для движения транспортных средств и людей на дорогах, площадках, про­\nездах и пешеходных переходах, в том числе открытые на время ремонта люки колодцев на инженерных \nсетях или люки колодцев с поврежденными крышками, следует немедленно ограждать.\n8.2 Техническое обслуживание\n8.2.1 Техническое обслуживание открытых грузовых складов и дорог должно включать: регуляр­\nные технические осмотры, периодические технические осмотры, внеочередные обследования.\n8.2.2 Регулярные технические осмотры открытых грузовых складов и дорог должны включать: \nпроверку технического состояния дорог и покрытий; проверку соблюдения установленного режима экс­\nплуатации; выявление дефектов и повреждений, возникающих в процессе эксплуатации и подлежащих \nнемедленной ликвидации.\nРегулярные технические осмотры открытых грузовых складов и дорог должны проводиться не \nреже одного раза в месяц.\n8.2.3 О случаях нарушения установленного режима эксплуатации открытых грузовых складов \nи дорог должно быть немедленно поставлено в известность руководство предприятия (завода), на \nтерритории которого обнаружены эти нарушения. Одновременно должны быть приняты меры к не­\nмедленному восстановлению условий эксплуатации в соответствии с установленными нормами и \nтребованиями.\n8.2.4 Периодические технические осмотры открытых грузовых складов и дорог рекомендуется \nпроводить в составе комплексных осмотров портовых сооружений не реже одного раза в год.\nПри периодических технических осмотрах должны тщательно и подробно проверяться техниче­\nское состояние открытых грузовых складов и дорог, а также режим их эксплуатации. При необходимо­\nсти следует выполнять наблюдения с использованием средств измерений.\n8.2.5 По результатам периодических технических осмотров следует планировать ремонтные ра­\nботы и мероприятия по подготовке открытых грузовых складов и дорог к эксплуатации в зимний или \nлетний период.\n8.2.6 При проведении регулярных и периодических технических осмотров необходимо обращать \nвнимание на следующие факторы, характеризующие состояние открытых грузовых складов и дорог:\n- состояние водоотводящих устройств; состояние обочин и кюветов (соответствие проектному \nпрофилю);\n- признаки пучения; волнистость, трещиноватость и размягчение асфальтобетонных покрытий; \nшелушения и выкрашивание асфальтобетона;\n- провалы асфальтобетона у колодцев подземных коммуникаций; поверхностные разрушения це- \nменто- и железобетонных покрытий (шелушение, отслоение, раковины); выбоины, трещины, проломы, \nсостояние швов и кромок цементо- и железобетонных покрытий (раскрытие швов, разрушение кромок, \nвыплески грунта через швы);\n- состояние плит сборных железобетонных покрытий (трещин, отколы, обнажения арматуры, кор­\nрозия и повреждение обрамляющих уголков и др.);\n- состояние укладки плит сборных железобетонных покрытий (состояние швов, плотность приле­\nгания плит к основанию, ровность поверхности покрытий);\n- состояние переездов через железнодорожные и подкрановые пути; наличие просадок покрытия \nс потерей уклонов и скоплениями воды во впадинах; состояние бордюрных камней;\n- наличие и состояние дорожных знаков; наличие и состояние разметки площадок, проездов и \nпешеходных дорожек.\n8.2.7 Внеочередные обследования следует проводить в случаях аварийных разрушений, появивших­\nся на территории открытых грузовых складов и на дорогах. По результатам внеочередных обследований\n14"
        },
        {
            "page": 19,
            "page_content": "СП 377.1325800.2017\nследует устанавливать временный режим эксплуатации открытых складов и дорог с поврежденными \nучастками и разрабатывать мероприятия по ликвидации повреждений.\n8.2.8 Уборку оперативной портовой территории или территории предприятия необходимо прово­\nдить систематически.\nВ зимний период снег и лед с дорог и проездов, а также с территории тех открытых грузовых скла­\nдов, которые предназначены для круглогодичной эксплуатации, следует регулярно убирать и вывозить.\nЗапрещается использовать для ускорения процесса таяния снега и льда такие химические средства, \nкоторые вызывают коррозию строительных материалов и наносят вред окружающей природной среде.\n8.2.9 При техническом обслуживании оперативной портовой территории или территории пред­\nприятия следует предусматривать работы по нанесению и обновлению линий разметки и окраске до­\nрожных знаков.\n8.3 Ремонт\n8.3.1 Порядок и организация работ по ремонту дорог и покрытий территории предприятий должны \nобеспечить:\n- увеличение сроков службы покрытий;\n- нормальные условия и безопасность движения безрельсового транспорта и людей;\n- снижение стоимости и увеличение сроков между ремонтами, а также рациональное расходова­\nние материальных ресурсов.\n8.3.2 При текущем ремонте дорог и покрытий территории предприятий особое внимание должно \nбыть обращено на следующие виды работ:\n- тщательную подготовку мест заделок и своевременную заделку поврежденных кромок и швов \nмонолитных цементобетонных покрытий (с обязательным проведением мероприятий, обеспечивающих \nсцепление бетона заделки со старым бетоном покрытия);\n- устранение неустойчивого состояния отдельных железобетонных плит сборных покрытий и вос­\nстановление их проектного положения;\n- своевременную заделку трещин и каверн в асфальтобетонных и монолитных цементобетонных \nпокрытиях;\n- обеспечение нормального водоотвода с поверхности дорог и покрытий.\n8.3.3 Капитальный ремонт дорог и покрытий портовой территории должен осуществляться силами \nспециализированных подрядных организаций.\n9 Рельсовые крановые пути\n9.1 Режим эксплуатации\n9.1.1 Техническая эксплуатация рельсовых крановых путей, расположенных на открытой террито­\nрии предприятия (завода), должна обеспечивать их долговечность и нормальную эксплуатацию кранов \nи перегружателей, а также машин специализированных перегрузочных комплексов.\n9.1.2 Для осуществления оперативного контроля за техническим состоянием рельсовых крановых \nпутей и режимом их эксплуатации на предприятии должна быть составлена схема крановых путей, \nнаходящихся на его территории, с указанием расстановки на путях портальных кранов и другого подъ­\nемно-транспортного оборудования.\n9.1.3 Для предотвращения значительных деформаций рельсовых крановых путей, препятствую­\nщих их нормальной эксплуатации, необходимо:\n- обеспечивать бесперебойную работу устройств для отвода воды от обеих ниток каждого пути;\n- не нарушать естественного сложения грунта в основании новых путей;\n- проводить предварительную обкатку крановых путей перед вводом их в эксплуатацию.\n9.1.4 Рельсовые крановые пути должны эксплуатироваться при соблюдении допусков, установ­\nленных [9], на отклонения от проектного положения, приведенные в [16].\n9.1.5 На участках рельсового кранового пути, где обнаружены крупные дефекты рельсов (выкол \nголовки, поперечный излом и т. п.), работа кранов запрещается:\n- при податливом (шпальном) основании — на расстоянии менее 3,0 м от оси переднего колеса \nкрана до дефектного участка рельса;\n- при жестком основании (железобетонные плиты и балки или железобетонное верхнее строение \nпричальных сооружений) — на расстоянии менее 1,0 м от оси переднего колеса крана до дефектного \nучастка рельса.\n15"
        },
        {
            "page": 20,
            "page_content": "СП 377.1325800.2017\nДля предотвращения возможной просадки на причалах прикордонной нитки кранового пути в тех \nслучаях, когда она не имеет свайного основания, а перед причалами обнаружены конусы выноса грун­\nта засыпки, дальнейшая эксплуатация кранового пути на участке возможной просадки не допускается \nвплоть до устранения причин выноса и полной компенсации вынесенного объема грунта.\n9.1.6 \nПри складировании груза вблизи от рельсовых крановых путей должны строго соблюдаться \nследующие габариты приближения к путям:\n- от штабеля до оси кранового рельса — не менее 2,0 м на уровне поверхности территории;\n- от штабеля до выступающих частей крана — не менее расстояний, приведенных в [9].\n9.2 Техническое обслуживание\n9.2.1 Техническое обслуживание рельсовых крановых путей должно включать следующие основ­\nные мероприятия:\n- осмотры крановых путей и наблюдения за их техническим состоянием, поддержание путей в ис­\nправности, включая своевременное обнаружение и устранение отклонений параметров кранового пути \nпо сравнению с установленными допусками;\n- систематическую замену отдельных износившихся или поврежденных элементов путей (шпал, \nрельсов, скреплений), содержание всей полосы путей в чистоте и порядке;\n- прочистка водоотводящих устройств.\n9.2.2 За техническим состоянием и режимом эксплуатации рельсовых крановых путей должны \nосуществляться наблюдения следующих видов: регулярные технические осмотры, периодические и \nвнеочередные осмотры с применением средств измерений.\n9.2.3 В процессе регулярного технического осмотра рельсовых крановых путей необходимо про­\nверять:\n- скрепление рельсов, при этом в случае необходимости производить восстановление и затяжку \nкрепежа;\n- состояние рельсового пути, стыков, плотность прилегания рельсов к шпалам, подкрановым пли­\nтам и балкам;\n- степень износа головки рельсов;\n- наличие трещин, накатов, изломов головки рельсов;\n- наличие коррозии рельсов и креплений;\n- состояние прирельсовых канавок;\n- крепление тупиковых упоров;\n- наличие повреждений деревянных шпал, в том числе вмятин, трещин, участков загнивания дре­\nвесины и т. д.;\n- наличие повреждений железобетонных шпал, плит и балок, в том числе трещин, раковин и т. д.;\n- состояние древесины, арматуры и бетона в местах крепления рельсов;\n- состояние балластного слоя;\n- состояние водоотводящих устройств;\n- состояние заземляющих устройств в соответствии с [13], [14].\n9.2.4 При регулярных технических осмотрах рельсовых крановых путей на жестком основании \nособое внимание следует обращать на состояние стыков, заметная осадка которых во время прохож­\nдения по ним крана указывает на разрушение бетона под стыками.\n9.2.5 Проверку положения рельсовых крановых путей на податливом (шпальном) основании с \nиспользованием средств измерений следует проводить не реже одного раза в шесть месяцев, а на \nжестком основании — не реже одного раза в год.\nВ случае если на причалах после введения их в эксплуатацию, возникли осадки засыпки в при­\nкордонной полосе, проверку положения рельсовых крановых путей на этих причалах рекомендуется \nпроводить ежемесячно.\n9.2.6 Нивелирование во время эксплуатации крановых путей следует проводить в точках рельсов, \nрасположенных друг от друга на расстоянии не далее чем через 10 м.\n9.2.7 Оценку высотного положения рельсовых крановых путей следует проводить на основе срав­\nнения полученных данных с допусками согласно [9] или с допусками поданным предприятий — постав­\nщиков оборудования. По результатам нивелирования следует проводить дополнительную проверку вы­\nсотного положения рельсов [16].\nДля крановых путей, уложенных на гидротехнических сооружениях эстакадного типа, указанная \nдополнительная проверка является обязательной.\n16"
        },
        {
            "page": 21,
            "page_content": "СП 377.1325800.2017\n9.2.8 Оценку планового положения рельсовых крановых путей следует проводить путем сравне­\nния отклонений в расстоянии между их осями относительно проектной ширины колеи с допусками, при­\nведенными в [16], или с допусками по данным предприятий — поставщиков оборудования.\n9.2.9 В процессе выполнения работ по техническому обслуживанию рельсовых крановых путей \nдля предупреждения расстройства путей следует систематически проводить подбивку балласта, смаз­\nку и подтягивание болтов, замену дефектных болтов и гаек, добивку костылей и т. п.\n9.3 Ремонт\n9.3.1 Производитель работ, перед тем как приступить к ремонтным работам на рельсовых крано­\nвых путях, должен получить разрешение на производство работ и наряд-допуск с указанием площадки, \nв пределах которой будет осуществляться ремонт.\n9.3.2 Перед началом ремонтных работ на рельсовых крановых путях при троллейном электро­\nпитании кранов следует отключить главные троллеи, на которых после этого должны быть поставлены \nвидимые заземления и соответствующие знаки безопасности по ГОСТ 12.4.026.\nРемонтируемые крановые пути необходимо ограждать упорами, на которых следует устанавли­\nвать днем красные флажки, а ночью — фонари.\n10 Прочие здания и сооружения\n10.1 Режим эксплуатации\n10.1.1 При установлении режима эксплуатации прочих зданий и сооружений портового или завод­\nского комплекса их следует подразделять, исходя из условий эксплуатации, на две группы:\n- первая группа — производственные здания и сооружения с технологическими процессами, вли­\nяющими на условия сохранности конструктивных элементов;\n- вторая группа — служебные, бытовые и вспомогательные здания и сооружения, конструктивные \nэлементы которых не подвергаются воздействиям при работе оборудования и транспортных средств.\nК первой группе относятся:\n- морские вокзалы;\n- гаражи внутрипортовой механизации и портовых автобаз;\n- автовесы; депо маневровых тепловозов порта;\n- ангары маломерных судов;\n- береговые радиолокационные станции (БРЛС) и центры (посты) регулирования движения судов \n(ЦРДС), ремонтно-механические мастерские;\n- здания технологических объектов ремонтно-строительных подразделений предприятий;\n- технологические объекты хозяйственных дворов ППК;\n- сооружения бункеровочных баз;\n- блоки санитарно-бытовых помещений; пожарные депо и др.\nКо второй группе относятся:\n- здания управления предприятий, а также конторы ППК и других производственных структурных \nподразделений;\n- портовые радиостанции, электрорадионавигационные камеры (ЭРНК);\n- здания бассейновых СЭС и их карантинных отделов [2];\n- здания контрольно-пропускных пунктов (КПП);\n- караульные помещения;\n- штормосигнальные, прожекторные и антенные мачты;\n- береговые сооружения и устройства навигационной обстановки, отдельно стоящие столовые, зда­\nния для обогрева рабочего персонала, санитарные узлы; охранное ограждение режимной территории и др.\n10.1.2 Техническая эксплуатация зданий и сооружений должна обеспечивать:\n- нормальные условия для работы размещенного в них оборудования и деятельности работников \nпредприятий;\n- сохранность и долговечность всех конструктивных элементов зданий и сооружений;\n- внешний вид, удовлетворяющий требованиям промышленной эстетики;\n- соблюдение противопожарных и санитарных требований и требований техники безопасности.\n10.1.3 Режим эксплуатации зданий и сооружений первой группы должен устанавливаться в соот­\nветствии с их назначением, на основании паспортных характеристик размещенного в них оборудования \nи данных о техническом состоянии основных конструктивных элементов.\n17"
        },
        {
            "page": 22,
            "page_content": "СП 377.1325800.2017\n10.1.4 Для зданий и сооружений первой группы, где складируют материалы, запасные части, гото­\nвые изделия и происходит движение транспорта, должны быть установлены нормы эксплуатационных \nнагрузок на полы и перекрытия.\nТаблицы допускаемых эксплуатационных нагрузок должны быть вывешены на видных местах.\n10.1.5 В зданиях и сооружениях первой группы установка технологического оборудования, не преду­\nсмотренного проектом, а также пробивка не предусмотренных проектом отверстий в стенах, перекрытиях, \nбалках и других конструктивных элементах зданий и сооружений без проверки расчетом несущей способ­\nности конструктивных элементов, воспринимающих нагрузку от оборудования, не допускаются.\nПревышение грузоподъемности перегрузочных средств, установленных в зданиях и сооружениях \nпервой группы, и вибрация при работе оборудования, превышающая значения, принятые в проекте, не \nдопускаются.\n10.1.6 При транспортировании и ремонте крупногабаритных агрегатов и деталей необходимо при­\nнимать меры к предотвращению повреждений конструктивных элементов зданий и сооружения.\n10.1.7 Не допускается складирование грузов снаружи стен зданий и сооружений в случае возник­\nновения от этих грузов дополнительных нагрузок на стены.\nВыброс отработанных воды и пара у стен зданий и сооружений не допускается.\n10.1.8 При технической эксплуатации зданий и сооружений, построенных на многолетнемерзлых \nгрунтах, должен строго выдерживаться заданный проектом температурный режим подвальных поме­\nщений, подполий и оснований.\n10.1.9 Требования к технической эксплуатации сооружений металлических резервуаров бункеро­\nвочных баз приведены в [10].\n10.1.10 При эксплуатации прожекторных и штормосигнальных мачт, а также опор наружного осве­\nщения, их отклонение от вертикальной оси не должно превышать:\n- для металлических мачт и опор — 1:200;\n- для железобетонных мачт и опор — 1:500.\n10.2 Техническое обслуживание\n10.2.1 Техническое обслуживание зданий и сооружений должно включать регулярные технические \nосмотры, периодические технические осмотры, специальные наблюдения с использованием средств \nизмерений, внеочередные обследования.\n10.2.2 Регулярные технические осмотры зданий и сооружений следует проводить не реже одного \nраза в три месяца.\n10.2.3 Периодические технические осмотры, наблюдения и внеочередные обследования с ис­\nпользованием средств измерений должны осуществляться в порядке, установленном в разделе 6.\n10.2.4 При проведении периодических технических осмотров зданий и сооружений их техническое со­\nстояние следует оценивать с учетом предельно допустимых смещений и деформаций, приведенных в [16].\n10.2.5 При техническом обслуживании зданий и сооружений, построенных на многолетнемерз­\nлых грунтах, наряду с наблюдениями за режимом их эксплуатации и техническим состоянием, следует \nвести наблюдения за температурами грунтов основания и температурой воздуха в проветриваемых \nпомещениях.\n10.2.6 Проверку металлических прожекторных и штормосигнальных мачт, а также опор наружного \nосвещения на коррозию следует проводить не реже одного раза в три года. Мачты и опоры, располо­\nженные в местах, где они подвергаются воздействию морской воды (брызги и водяная пыль) или других \nагрессивных сред, рекомендуется подвергать проверке на коррозию ежегодно. Для выявления степени \nповреждения металла с его поверхности тщательно удаляют продукты коррозии, после чего замеряют \nсечения элементов. Уменьшение площади расчетного поперечного сечения элементов металлокон­\nструкций мачт и опор не должно превышать 20 %.\n10.3 Ремонт\n10.3.1 Производственные структурные подразделения порта должны выполнять работы по те­\nкущему ремонту используемых ими зданий и сооружений в соответствии с перечнем, установленным \nраспоряжением по предприятию.\n10.3.2 При ремонте и окраске фасадов зданий и сооружений, расположенных на территории \nпредприятия (завода), должны соблюдаться требования технической эстетики. Эти требования должны \nбыть отражены в технической документации на ремонт зданий и сооружений.\n18"
        },
        {
            "page": 23,
            "page_content": "СП 377.1325800.2017\nФасады зданий и сооружений, которые выходят на городские магистрали и акватории города, \nследует окрашивать водостойкими красками. При этом цветовое решение фасадов следует выбирать в \nзависимости от климатического района (северные — активная цветовая гамма, южные — гамма свет­\nлых тонов).\n10.3.3 Ремонт металлических резервуаров должен выполняться в соответствии с [10].\n10.3.4 Ремонт прожекторных мачт и опор наружного освещения должен выполняться по заявкам \nпредприятия (завода): железобетонных — его ремонтно-строительным подразделением, металличе­\nских— производственными мастерскими предприятия (завода).\n10.3.5 Ремонт штормосигнальных мачт должен выполняться по заявкам службы портнадзора ре­\nмонтно-строительным подразделением порта.\n10.3.6 Ремонт охранных ограждений предприятия (завода) должен выполняться по требованиям \nподразделения военизированной охраны (ВОХР) в зависимости от вида ремонта или ремонтно-строи­\nтельным подразделением предприятия (завода).\n11 Акватории и судоходные каналы\n11.1 Режим эксплуатации\n11.1.1 Техническая эксплуатация акваторий портов и их судоходных каналов должна обеспечи­\nвать безаварийное плавание и стоянку судов в порту.\nНа судоремонтных заводах техническая эксплуатация акватории должна обеспечивать безава­\nрийное плавание и стоянку судов, ремонтируемых СРЗ, а также безопасную и эффективную работу \nсудоподъемных сооружений.\n11.1.2 Режим эксплуатации акватории предприятий, составляющей отведенные ей в установлен­\nном порядке водные пространства, в составе гаваней, внутреннего и внешнего рейдов, разворотных \nковшей и фарватеров, а также судоходных каналов предприятий должен устанавливаться в соответ­\nствии с [11], [1] с учетом их паспортных характеристик и технического состояния.\n11.1.3 Осадка судов, принимаемых портом в течение навигационного периода, должна объявлять­\nся приказом по порту и вноситься в обязательные постановления в морском порту, разработанные в \nсоответствии с [1].\n11.1.4 В приливных портах глубины у причалов должны обеспечивать безопасную стоянку судов в \nполном грузу в период сизигийных отливов или же режим эксплуатации причалов должен быть регла­\nментирован специальными указаниями.\n11.1.5 Акватория и судоходные каналы предприятий должны быть оснащены средствами навига­\nционного оборудования (СНО).\n11.1.6 При изменении глубины на канале и на судоходных участках акватории порта должна быть \nсоответствующим образом изменена расстановка знаков навигационной обстановки с оповещением об \nэтом судоводителя.\n11.1.7 При повреждении знаков навигационной обстановки или их неисправности капитан порта \n(завода), руководствуясь [12], должен принять срочные меры, обеспечивающие безопасность движения \nсудов, и дать указание об исправлении обстановки.\n11.1.8 Капитан судна при обнаружении обмеления на канале или акватории порта, отсутствия \nзнаков навигационной обстановки или их смещения со штатных мест, отсутствия огней на знаках в \nакватории и на территории порта должен немедленно сообщить об этом службе капитана порта в со­\nответствии с [1].\n11.1.9 Если на акватории предприятия судном утерян якорь или другой предмет, представляющий \nопасность для судоходства, капитан судна должен, с ведома капитана порта (завода), принять необхо­\nдимые меры, чтобы поднять утерянный предмет. Если последний не будет найден, следует немедленно \nобозначить район потопления и сообщить об этом капитану порта (СРЗ).\n11.1.10 Не допускается без особых обоснований возведение или установка в пределах аквато­\nрии и судоходных каналов предприятия каких-либо сооружений или устройств, стесняющих движение \nсудов.\n11.1.11 Для предотвращения возможности повреждения подводных кабелей и трубопроводов в \nслучае, если их трассы при любом виде прокладки пересекают акваторию или судоходные каналы \nпредприятия, должны быть установлены охранные зоны.\n19"
        },
        {
            "page": 24,
            "page_content": "СП 377.1325800.2017\nВ охранных зонах запрещается: бросать якоря, проходить с отданными якорями, цепями, люками, \nволокушами и тралами, производить погрузочно-разгрузочные и дноуглубительные работы, приставать \nк берегу в местах, огражденных сигнальными знаками.\nВсе работы, которые должны быть выполнены в охранных зонах, а также вблизи от них, следует \nпредварительно согласовать с предприятиями (организациями), в ведении которых находятся подво­\nдные кабели и трубопроводы.\n11.1.12 \nКонтроль за соблюдением установленного режима эксплуатации и обеспечением гаранти­\nрованных габаритов акватории и судоходных каналов предприятия следует осуществлять путем регу­\nлярных наблюдений за состоянием их глубин.\nНа территории, прилегающей к акватории и судоходным каналам, для удобства проведения про­\nмерных и дноуглубительных работ должна быть создана постоянная геодезическая сеть.\n11.2 Техническое обслуживание\n11.2.1 Порядок и организация работ по техническому обслуживанию и ремонту акваторий и судо­\nходных каналов должны обеспечивать:\n- поддержание требуемых навигационных габаритов ремонтным дноуглублением;\n- выполнение промерных и тральных работ, связанных с производством ремонтных дноуглуби­\nтельных работ и обеспечением безопасного судоходства на обслуживаемых участках пути, безопас­\nность и эффективность работы судоподъемных сооружений заводов;\n- соблюдение габаритов СНО и их обслуживание;\n- соблюдение требований органов государственного контроля за состоянием окружающей при­\nродной среды.\nПо заданиям пароходства могут быть внесены изменения в габариты акваторий и судоходных \nканалов предприятий по требованиям условий эксплуатации.\n11.2.2 На акваториях и судоходных каналах предприятий необходимо систематически выполнять \nследующие работы по их техническому обслуживанию:\n- проводить промеры глубин;\n- осуществлять наблюдения за чистотой вод акваторий и судоходных каналов;\n- проводить очистку дна от различного рода предметов, мешающих судоходству.\n11.2.3 Периодичность промерных и тральных работ должна устанавливаться администрацией \nпредприятий в зависимости от действия гидрометеорологических факторов и интенсивности отложе­\nния наносов на обслуживаемых акваториях и судоходных каналах.\n11.2.4 На основании данных промеров должны составляться планы глубин судоходных каналов \nи судоходных частей акватории, а также определяться толщина слоя наносов и объем необходимых \nдноуглубительных работ.\n11.2.5 При осуществлении гарантийного технического обслуживания акваторий и судоходных ка­\nналов бассейновое управление внутренних водных путей должно систематически информировать за­\nказчика (предприятие) о состоянии габаритов на обслуживаемых участках пути.\nПо требованию капитана порта (СРЗ), осуществляющего контроль за поддержанием необхо­\nдимых глубин на акватории и судоходных каналах, подразделения бассейнового управления вну­\nтренних водных путей обязаны выполнять внеочередные контрольные промеры глубин на лимити­\nрующих участках канала или акватории, когда это вызвано необходимостью безопасной проводки \nсудов.\n11.2.6 Контроль за исправным действием СНО на предприятии (заводе) возлагается на капитана \nпорта (СРЗ).\n11.2.7 На все акватории и судоходные каналы предприятий должны быть составлены паспорта, \nразрабатываемые проектной организацией по заказу предприятий.\nКорректировка паспортов существующих акваторий и судоходных каналов должна по мере необ­\nходимости осуществляться службой капитана порта СРЗ совместно с проектной организацией.\n11.3 Ремонтные дноуглубительные работы\n11.3.1 \nДля определения объема намеченных ремонтных дноуглубительных работ, а также для \nполучения разрешения на их выполнение и сброс грунта в море от органов государственного контроля \nза охраной окружающей среды в администрации порта или предприятия (завода) должны систе­\nматизироваться и храниться материалы, характеризующие строение дна акваторий и судоходных\n20"
        },
        {
            "page": 25,
            "page_content": "СП 377.1325800.2017\nканалов, сведения об интенсивности заносимости и о физико-механических, а также химико-биологи­\nческих свойствах донных грунтов.\n11.3.2 Сроки выполнения ремонтных дноуглубительных работ следует назначать в зависимости от \nинтенсивности заносимости, принятых запасов на заносимость и установленной ширины углубляемой \nполосы, а также с учетом технико-эксплуатационных характеристик применяемых дноуглубительных \nсредств.\n11.3.3 Согласование сроков и объема производства ремонтных дноуглубительных работ, а также \nмест отвалов грунта с государственными органами контроля за состоянием окружающей природной \nсреды должен проводить заказчик с привлечением проектной организации. Материалы для согласова­\nния и получения разрешений на ремонтные дноуглубительные работы и отвалы грунта, должна гото­\nвить проектная организация.\n11.3.4 Годовой план ремонтных дноуглубительных работ, включающих обследование дна ак­\nваторий и судоходных каналов, очистку их от затонувших предметов, а также подчистку у причалов, \nизвлечение и удаление грунта, должен составляться для заказчика (предприятия), финансирующего \nуказанные работы, бассейновым управлением внутренних водных путей. Годовой план ремонтных дно­\nуглубительных работ должен быть согласован с главным инженером и капитаном порта (завода).\n11.3.5 В техническом задании на производство ремонта дноуглубительных работ у гидротехни­\nческих сооружений или в районах трасс подводных инженерных коммуникаций во избежание их по­\nвреждения должны быть указаны безопасные расстояния от границ рабочей прорези до лицевой грани \nсооружения и от трасс до грунтозаборного устройства и якорей земснаряда.\n11.3.6 При производстве ремонтных дноуглубительных работу гидротехнических сооружений ве­\nличина допускаемого перебора глубины на чистоту выработки прорези должна определяться предпри­\nятием (заводом) в зависимости от конструкции сооружения и технического средства дноуглубления по \nсогласованию с проектной организацией.\n11.3.7 При транспортировании грунта в процессе ремонтных дноуглубительных работ должно \nбыть исключено засорение дна акваторий и судоходных каналов грунтом из люков грунтоотвозных су­\nдов или рефулерных устройств.\n11.3.8 Ответственность за регулирование движения судов по акватории и судоходным каналам \nпредприятия, обеспечивающее безопасность мореплавания, возлагается на капитана порта (завода).\nВ случае обнаружения нарушений судами правил плавания и эксплуатации акваторий и причаль­\nных сооружений в порту, следствием чего явилось или может явиться ухудшение их эксплуатационного \nсостояния, капитану порта через государственный портовый контроль в соответствии с [2, ст. 38.1] сле­\nдует принять меры к их пресечению и в нужных случаях составить протокол о нарушении для привле­\nчения виновных к ответственности.\n11.3.9 Ответственность за отдачу якорей в местах прохождения подводных кабелей, обозначен­\nных предупредительными знаками, несет судовая администрация.\n11.3.10 При повреждении судами оборудования рейдовых причалов и плавучих знаков навигаци­\nонной обстановки ответственность несет судовая администрация.\n11.3.11 Руководители ремонтных дноуглубительных работ на акватории и судоходных каналах \nобязаны согласовать порядок проведения этих работ с капитаном порта (завода).\n21"
        },
        {
            "page": 26,
            "page_content": "СП 377.1325800.2017\nБиблиография\n[1] \nФедеральный закон от 8 ноября 2007 г. № 261-ФЗ «О морских портах в Российской Федерации и о внесении \nизменений в отдельные законодательные акты Российской Федерации»\n[2] \nФедеральный закон от 7 марта 2001 г. № 24-ФЗ «Кодекс внутреннего водного транспорта Российской Феде­\nрации»\n[3] \nФедеральный закон от 22 июля 2008 г. № 123-ФЗ «Технический регламент о требованиях пожарной безопас­\nности»\n[4] \nПостановление Правительства Российской Федерации от 12 августа 2010 г. № 620 «Об утверждении техниче­\nского регламента о безопасности объектов морского транспорта»\n[5] \nПостановление Правительства Российской Федерации от 12 августа 2010 г. № 623 «Об утверждении техниче­\nского регламента о безопасности объектов внутреннего водного транспорта»\n[6] \nПостановление Правительства Российской Федерации от 29 октября 2010 г. № 870 «Об утверждении техниче­\nского регламента о безопасности сетей газораспределения и газопотребления»\n[7] \nПриказ Минтранса России от 21 декабря 2010 г. № 286 «Об утверждении Правил технической эксплуатации \nжелезных дорог Российской Федерации»\n[8] \nПриказ Минтруда России от 24 июля 2013 г. № 328н «Об утверждении Правил по охране труда при эксплуата­\nции электроустановок»\n[9] \nПриказ Ростехнадзора от 12 ноября 2013 г. № 533 «Об утверждении Федеральных норм и правил в области \nпромышленной безопасности «Правила безопасности опасных производственных объектов, на которых ис­\nпользуются подъемные сооружения»\n[10] Приказ Минэнерго России от 19 июня 2003 г. № 232 «Об утверждении Правил технической эксплуатации \nнефтебаз»\n[11] Приказ Минтранса России от 20 августа 2009 г. № 140 «Об утверждении Общих правил плавания и стоянки \nсудов в морских портах Российской Федерации и на подходах к ним»\n[12] Приказ Минтранса России от 17 февраля 2014 г. № 39 «Об утверждении Положения о капитане морского \nпорта»\n[13] Правила устройства электроустановок (ПУЭ)\n[14] Приказ Минэнерго России от 13 января 2003 г. № 6 «Об утверждении Правил технической эксплуатации элек­\nтроустановок потребителей»\n[15] ОДМ 218.2.036—2013 Методические рекомендации по устройству, ремонту, содержанию и эксплуатации па­\nромных переправ и наплавных мостов\n[16] РД 31.35.10—86 Правила технической эксплуатации портовых сооружений и акваторий\n[17] РД 31.66.03—85 Правила технического обслуживания и ремонта оборудования и сооружений радиосвязи бе­\nреговых предприятий ММФ\n22"
        },
        {
            "page": 27,
            "page_content": "СП 377.1325800.2017\nУДК 69.034.3 \nОКС 93.140\nКлючевые слова: сооружения портовые, гидротехнические сооружения, крытые, открытые склады, до­\nроги, рельсовые пути, прочие здания и сооружения, акватории, судоходные каналы, правила эксплуа­\nтации\n23"
        },
        {
            "page": 28,
            "page_content": "Технический редактор В.Н. Прусакова \nКорректор Е.Р. Ароян \nКомпьютерная верстка Ю.В. Поповой\nСдано в набор 09.08.2018. \nПодписано в печать 13.08.2018. \nФормат 60 * 841/g. \nГарнитура Ариал.\nУел. печ. л. 3,26. \nУч.-изд. л. 3,16.\nПодготовлено на основе электронной версии, предоставленной разработчиком свода правил\nИД «Юриспруденция», 115419, Москва, ул. Орджоникидзе, 11. \nwww.jurisizdat.ru \ny-book@mail.ru\nСоздано в единичном исполнении ФГУП «СТАНДАРТИНФОРМ» \nдля комплектования Федерального информационного фонда стандартов, \n123001 Москва, Гранатный пер., 4. \nwww.gostinfo.ru \ninfo@gostinfo.ru\nСП 377.1325800.2017"
        }
    ],
    "confidence_scores": {
        "full_name": 0.95,
        "number": 0.98,
        "date_issue": 0.95,
        "type": 0.99,
        "category": 0.9
    }
}